stonefish_license_creator/__init__.py
stonefish_license_creator/_cli.py
stonefish_license_creator/_console.py
stonefish_license_creator/_crypto.py
stonefish_license_creator/_helpers.py
stonefish_license_creator/_license_validation.py
stonefish_license_creator/_main.py
stonefish_license_creator-0.1.5.dist-info/METADATA
stonefish_license_creator-0.1.5.dist-info/WHEEL
stonefish_license_creator-0.1.5.dist-info/entry_points.txt
stonefish_license_creator-0.1.5.dist-info/top_level.txt
stonefish_license_creator-0.1.5.dist-info/RECORD
