Metadata-Version: 2.2
Name: stonefish-license-creator
Version: 0.1.5
Summary: Stonefish license creator for Python
Author-email: Nico Schlömer <nico.schloemer@gmail.com>
Project-URL: Homepage, https://github.com/stonefish-dev/license-creator
Project-URL: Issues, https://github.com/stonefish-dev/license-creator/issues
Classifier: Development Status :: 4 - Beta
Classifier: License :: Other/Proprietary License
Classifier: Operating System :: OS Independent
Classifier: Programming Language :: Python
Classifier: Programming Language :: Python :: 3 :: Only
Classifier: Programming Language :: Python :: 3.9
Classifier: Programming Language :: Python :: 3.10
Classifier: Programming Language :: Python :: 3.11
Classifier: Programming Language :: Python :: 3.12
Classifier: Programming Language :: Python :: 3.13
Classifier: Topic :: Utilities
Requires-Python: >=3.9
Requires-Dist: x21 (>=0.5.3)
Requires-Dist: cryptography
Requires-Dist: isodate
Requires-Dist: jsonschema[format]
Requires-Dist: py-machineid
Requires-Dist: pyyaml
Requires-Dist: rich
Requires-Dist: rich-argparse
Requires-Dist: stonefish-license-manager>=0.4.5
